<?xml version="1.0" encoding="ISO_8859-1"?>
<user name="editorA" realm="local">
	<owner name="administrator" realm="local" />
	<realName>Bearbeiter für Personen</realName>
	<eMail>editorA@my-email.xy</eMail>
	<roles>
		<role name="adminperson" />
	</roles>
	<attributes>
		<attribute name="description" value="Berechtigter Editor für Personen (Workflow)" />
		<attribute name="sex" value="male" />
		<attribute name="institution" value="" />
		<attribute name="street" value="" />
		<attribute name="city" value="" />
		<attribute name="postalcode" value="" />
		<attribute name="tel" value="" />
	</attributes>
	 <password hashType="sha1" hash="editorA" />
</user>