<?xml version="1.0" encoding="UTF-8"?>
<mycorederivate xmlns:xsi="http://www.w3.org/2001/XMLSchema-instance" xmlns:xlink="http://www.w3.org/1999/xlink" ID="DocPortal_derivate_00410904" label="Datenobjekte zu DocPortal_document_00410904" xsi:noNamespaceSchemaLocation="datamodel-derivate.xsd"><derivate><linkmetas class="MCRMetaLinkID" heritable="false" parasearch="true" textsearch="false"><linkmeta inherited="0" xlink:type="locator" xlink:href="DocPortal_document_00410904"/></linkmetas><internals class="MCRMetaIFS" heritable="false" notinherit="true" parasearch="false" textsearch="false"><internal sourcepath="docportal_derivate_00410904" maindoc="bilder_10_de.html" /></internals></derivate><service><servdates class="MCRMetaDate" heritable="false" notinherit="false" parasearch="true" textsearch="false"><servdate xml:lang="de" inherited="0" type="createdate">2004-06-04</servdate><servdate xml:lang="de" inherited="0" type="modifydate">2004-06-04</servdate></servdates></service></mycorederivate>
